pheval_exomiser/__init__.py
pheval_exomiser/cli.py
pheval_exomiser/constants.py
pheval_exomiser/post_process/__init__.py
pheval_exomiser/post_process/post_process.py
pheval_exomiser/post_process/post_process_results_format.py
pheval_exomiser/prepare/__init__.py
pheval_exomiser/prepare/create_batch_commands.py
pheval_exomiser/prepare/tool_specific_configuration_options.py
pheval_exomiser/prepare/write_application_properties.py
pheval_exomiser/run/__init__.py
pheval_exomiser/run/run.py
pheval_exomiser/runner.py
pheval_exomiser-0.4.6.dist-info/METADATA
pheval_exomiser-0.4.6.dist-info/WHEEL
pheval_exomiser-0.4.6.dist-info/entry_points.txt
pheval_exomiser-0.4.6.dist-info/RECORD
